Metadata-Version: 1.1
Name: djnext
Version: 0.0.1
Summary: Django-NextJS Isomorphic UI dev with Decorator pattern
Home-page: https://git.yourlabs.org/oss/djnext
Author: James Pic
Author-email: jamespic@gmail.com
License: MIT
Keywords: django nextjs
Platform: UNKNOWN
Classifier: Development Status :: 1 - Planning
Classifier: Environment :: Web Environment
Classifier: Framework :: Django
Classifier: Intended Audience :: Developers
Classifier: License :: OSI Approved :: MIT License
Classifier: Operating System :: OS Independent
Classifier: Programming Language :: Python
Classifier: Programming Language :: Python :: 3
Classifier: Topic :: Internet :: WWW/HTTP
Classifier: Topic :: Software Development :: Libraries :: Python Modules
